setup.py
bin/showtime
showtime/__init__.py
showtime.egg-info/PKG-INFO
showtime.egg-info/SOURCES.txt
showtime.egg-info/dependency_links.txt
showtime.egg-info/not-zip-safe
showtime.egg-info/requires.txt
showtime.egg-info/top_level.txt