Metadata-Version: 1.0
Name: showtime
Version: 0.7
Summary: Stream movies/seasons directly to your vlc. Visit https://github.com/rahulxxarora/showtime for docs
Home-page: https://github.com/rahulxxarora/showtime
Author: Rahul Arora
Author-email: coderahul94@gmail.com
License: MIT
Platform: UNKNOWN
